MANIFEST.in
NEWS.txt
README.rst
setup.py
src/django_photos.egg-info/PKG-INFO
src/django_photos.egg-info/SOURCES.txt
src/django_photos.egg-info/dependency_links.txt
src/django_photos.egg-info/entry_points.txt
src/django_photos.egg-info/not-zip-safe
src/django_photos.egg-info/requires.txt
src/django_photos.egg-info/top_level.txt
src/photos/__init__.py
src/photos/admin.py
src/photos/models.py
src/photos/urls.py
src/photos/views.py
src/photos/templates/404.html
src/photos/templates/500.html
src/photos/templates/admin/photos/photo/change_list.html
src/photos/templates/photos/admin_thumbnail.html
src/photos/templates/photos/album_detail.html
src/photos/templates/photos/album_list.html
src/photos/templates/photos/base.html
src/photos/templates/photos/photo_detail.html
src/photos/templates/photos/photo_list.html
src/photos/templatetags/__init__.py
src/photos/templatetags/photos_extras.py
src/photos/tests/__init__.py
src/photos/tests/models.py
src/photos/tests/tests.py
src/photos/tests/urls.py
src/photos/tests/static/a.jpg
src/photos/tests/static/b.jpg
src/photos/tests/static/c.jpg