Metadata-Version: 1.0
Name: django-photos
Version: 0.2.10
Summary: This is a simple photo-app for django.
Home-page: http://www.bitbucket.org/feuervogel/django-photos
Author: Julian Moritz
Author-email: jumo@gmx.de
License: BSD
Keywords: django photo gallery
Platform: UNKNOWN
Classifier: Development Status :: 3 - Alpha
Classifier: Environment :: Web Environment
Classifier: Framework :: Django
Classifier: Intended Audience :: Developers
Classifier: License :: OSI Approved :: BSD License
Classifier: Natural Language :: English
Classifier: Programming Language :: Python
Classifier: Topic :: Internet :: WWW/HTTP :: Dynamic Content
